pyoctave/__init__.py
pyoctave/version.py
pyoctave-2.0.0.dist-info/METADATA
pyoctave-2.0.0.dist-info/WHEEL
pyoctave-2.0.0.dist-info/top_level.txt
pyoctave-2.0.0.dist-info/RECORD
